victoria_gwemail_rebuilder/__init__.py
victoria_gwemail_rebuilder/cli.py
victoria_gwemail_rebuilder/client.py
victoria_gwemail_rebuilder/config.py
victoria_gwemail_rebuilder/rebuild.py
victoria_gwemail_rebuilder-0.0.2.dist-info/LICENSE
victoria_gwemail_rebuilder-0.0.2.dist-info/METADATA
victoria_gwemail_rebuilder-0.0.2.dist-info/WHEEL
victoria_gwemail_rebuilder-0.0.2.dist-info/top_level.txt
victoria_gwemail_rebuilder-0.0.2.dist-info/RECORD
