Metadata-Version: 2.1
Name: victoria-gwemail-rebuilder
Version: 0.0.2
Summary: Victoria Plugin that allows the creation and DESTRUCTION of Glasswall Email on the cloud.
Home-page: UNKNOWN
Author: Josh Moulder
License: UNKNOWN
Platform: UNKNOWN
License-File: LICENSE
Requires-Dist: click
Requires-Dist: marshmallow
Requires-Dist: pyyaml
Requires-Dist: requests
Requires-Dist: azure-devops
Requires-Dist: victoria
